{
	"root":"http://onx1obrfu.bkt.clouddn.com/joystorage/photos/",
	"min":"http://onx1obrfu.bkt.clouddn.com/joystorage/photo-min/",
	"mid":"http://onx1obrfu.bkt.clouddn.com/joystorage/photo-mid/",
	"contents":[
		{"title":"毕业","pre":"毕业","data":[{"url":"1.jpg"},{"url":"2.jpg"},{"url":"3.jpg"}]},
		{"title":"黑龙江·哈尔滨","pre":"哈尔滨","data":[{"url":"1.jpg"},{"url":"2.jpg"},{"url":"3.jpg"},{"url":"4.jpg"},{"url":"5.jpg"},{"url":"6.jpg"},{"url":"7.jpg"},{"url":"8.jpg"}]},
		{"title":"吉林·长春","pre":"长春","data":[{"url":"1.jpg"},{"url":"2.jpg"},{"url":"3.jpg"}]},
		{"title":"辽宁·沈阳","pre":"沈阳","data":[{"url":"1.jpg"},{"url":"2.jpg"},{"url":"3.jpg"},{"url":"4.jpg"}]},
		{"title":"北京","pre":"北京","data":[{"url":"1.jpg"},{"url":"2.jpg"},{"url":"3.jpg"},{"url":"4.jpg"},{"url":"5.jpg"}]},
		{"title":"上海","pre":"上海","data":[{"url":"1.jpg"},{"url":"2.jpg"},{"url":"3.jpg"}]},
		{"title":"浙江·杭州","pre":"杭州","data":[{"url":"1.jpg"},{"url":"2.jpg"},{"url":"3.jpg"},{"url":"4.jpg"}]},
		{"title":"湖北·武汉","pre":"武汉","data":[{"url":"1.jpg"},{"url":"2.jpg"},{"url":"3.jpg"},{"url":"4.jpg"}]},
		{"title":"湖北·宜昌","pre":"","data":[{"url":"1.jpg"},{"url":"2.jpg"},{"url":"3.jpg"},{"url":"4.jpg"},{"url":"5.jpg"},{"url":"6.jpg"}]},
		{"title":"福建·厦门","pre":"厦门","data":[{"url":"1.jpg"},{"url":"2.jpg"},{"url":"3.jpg"},{"url":"4.jpg"}]},
		{"title":"福建·福州","pre":"福州","data":[{"url":"1.jpg"},{"url":"2.jpg"},{"url":"3.jpg"},{"url":"4.jpg"}]},
		{"title":"广东·深圳","pre":"深圳","data":[{"url":"1.jpg"},{"url":"3.jpg"},{"url":"8.jpg"},{"url":"7.jpg"}]},	
		{"title":"澳门","pre":"澳门","data":[{"url":"1.jpg"},{"url":"2.jpg"},{"url":"3.jpg"}]}
	]
}